README.rst
setup.py
jingenr/__init__.py
jingenr.egg-info/PKG-INFO
jingenr.egg-info/SOURCES.txt
jingenr.egg-info/dependency_links.txt
jingenr.egg-info/top_level.txt