Metadata-Version: 1.1
Name: jingenr
Version: 0.0.1
Summary: Replication of Model II from Jin et al (2001)
Home-page: https://github.com/jbn/jin_et_al_2001
Author: John Bjorn Nelson
Author-email: jbn@pathdependent.com
License: MIT
Keywords: sna sociology sociogenesis
Platform: UNKNOWN
Classifier: Development Status :: 3 - Alpha
Classifier: Intended Audience :: Science/Research
Classifier: Topic :: Sociology
Classifier: License :: OSI Approved :: MIT License
Classifier: Programming Language :: Python :: 2.7
Classifier: Programming Language :: Python :: 3
Classifier: Programming Language :: Python :: 3.2
Classifier: Programming Language :: Python :: 3.3
Classifier: Programming Language :: Python :: 3.4
